[{"title": "Vienna", "lat": "48.2083", "long": "16.3725"}, {"title": "Graz", "lat": "47.0708", "long": "15.4386"}, {"title": "Linz", "lat": "48.3058", "long": "14.2864"}, {"title": "Salzburg", "lat": "47.8000", "long": "13.0450"}, {"title": "Innsbruck", "lat": "47.2683", "long": "11.3933"}, {"title": "Klagenfurt", "lat": "46.6167", "long": "14.3000"}, {"title": "Sankt Polten", "lat": "48.2000", "long": "15.6167"}, {"title": "Bregenz", "lat": "47.5050", "long": "9.7492"}, {"title": "Modling", "lat": "48.0856", "long": "16.2831"}, {"title": "Hall in Tirol", "lat": "47.2833", "long": "11.5000"}, {"title": "Eisenstadt", "lat": "47.8500", "long": "16.5167"}, {"title": "Villach", "lat": "46.6167", "long": "13.8333"}, {"title": "Wels", "lat": "48.1500", "long": "14.0167"}, {"title": "Dornbirn", "lat": "47.4167", "long": "9.7500"}, {"title": "Wiener Neustadt", "lat": "47.8167", "long": "16.2500"}, {"title": "Steyr", "lat": "48.0333", "long": "14.4167"}, {"title": "Leonding", "lat": "48.2792", "long": "14.2528"}, {"title": "Klosterneuburg", "lat": "48.3042", "long": "16.3167"}, {"title": "Baden", "lat": "48.0075", "long": "16.2344"}, {"title": "Traun", "lat": "48.2217", "long": "14.2397"}, {"title": "Wolfsberg", "lat": "46.8419", "long": "14.8408"}, {"title": "Krems an der Donau", "lat": "48.4167", "long": "15.6167"}, {"title": "Leoben", "lat": "47.3817", "long": "15.0972"}, {"title": "Amstetten", "lat": "48.1167", "long": "14.8667"}, {"title": "Lustenau", "lat": "47.4271", "long": "9.6711"}, {"title": "Kapfenberg", "lat": "47.4394", "long": "15.2894"}, {"title": "Hallein", "lat": "47.6667", "long": "13.0833"}, {"title": "Kufstein", "lat": "47.5833", "long": "12.1667"}, {"title": "Traiskirchen", "lat": "48.0189", "long": "16.2922"}, {"title": "Schwechat", "lat": "48.1411", "long": "16.4786"}, {"title": "Stockerau", "lat": "48.3858", "long": "16.2108"}, {"title": "Braunau am Inn", "lat": "48.2583", "long": "13.0333"}, {"title": "Hohenems", "lat": "47.3667", "long": "9.6667"}, {"title": "Saalfelden am Steinernen Meer", "lat": "47.4269", "long": "12.8483"}, {"title": "Ansfelden", "lat": "48.2083", "long": "14.2889"}, {"title": "Telfs", "lat": "47.3069", "long": "11.0722"}, {"title": "Bruck an der Mur", "lat": "47.4106", "long": "15.2686"}, {"title": "Perchtoldsdorf", "lat": "48.1167", "long": "16.2667"}, {"title": "Spittal an der Drau", "lat": "46.7917", "long": "13.4958"}, {"title": "Bludenz", "lat": "47.1533", "long": "9.8219"}, {"title": "Ternitz", "lat": "47.7167", "long": "16.0333"}, {"title": "Worgl", "lat": "47.4831", "long": "12.0664"}, {"title": "Schwaz", "lat": "47.3500", "long": "11.7000"}, {"title": "Feldkirchen", "lat": "46.7236", "long": "14.0919"}, {"title": "Korneuburg", "lat": "48.3453", "long": "16.3331"}, {"title": "Hard", "lat": "47.4892", "long": "9.6900"}, {"title": "Bad Ischl", "lat": "47.7115", "long": "13.6239"}, {"title": "Marchtrenk", "lat": "48.1917", "long": "14.1106"}, {"title": "Feldbach", "lat": "46.9550", "long": "15.8883"}, {"title": "Knittelfeld", "lat": "47.2150", "long": "14.8294"}, {"title": "Neunkirchen", "lat": "47.7269", "long": "16.0817"}, {"title": "Brunn am Gebirge", "lat": "48.1069", "long": "16.2842"}, {"title": "Gmunden", "lat": "47.9181", "long": "13.7994"}, {"title": "Vocklabruck", "lat": "48.0086", "long": "13.6558"}, {"title": "Sankt Veit an der Glan", "lat": "46.7667", "long": "14.3603"}, {"title": "Leibnitz", "lat": "46.7831", "long": "15.5450"}, {"title": "Lienz", "lat": "46.8297", "long": "12.7697"}, {"title": "Rankweil", "lat": "47.2667", "long": "9.6500"}, {"title": "Enns", "lat": "48.2167", "long": "14.4750"}, {"title": "Weiz", "lat": "47.2189", "long": "15.6253"}, {"title": "Gotzis", "lat": "47.3342", "long": "9.6453"}, {"title": "Bad Voslau", "lat": "47.9669", "long": "16.2144"}, {"title": "Ried im Innkreis", "lat": "48.2100", "long": "13.4894"}, {"title": "Gross-Enzersdorf", "lat": "48.2000", "long": "16.5500"}, {"title": "Ganserndorf", "lat": "48.3406", "long": "16.7175"}, {"title": "Hollabrunn", "lat": "48.5667", "long": "16.0833"}, {"title": "Deutschlandsberg", "lat": "46.8161", "long": "15.2150"}, {"title": "Mistelbach", "lat": "48.5667", "long": "16.5667"}, {"title": "Gerasdorf bei Wien", "lat": "48.2950", "long": "16.4675"}, {"title": "Waidhofen an der Ybbs", "lat": "47.9596", "long": "14.7745"}, {"title": "Sankt Johann im Pongau", "lat": "47.3500", "long": "13.2000"}, {"title": "Trofaiach", "lat": "47.4261", "long": "15.0067"}, {"title": "Ebreichsdorf", "lat": "47.9611", "long": "16.4047"}, {"title": "Gleisdorf", "lat": "47.1039", "long": "15.7083"}, {"title": "Volkermarkt", "lat": "46.6622", "long": "14.6344"}, {"title": "Wiener Neudorf", "lat": "48.0856", "long": "16.3131"}, {"title": "Zwettl", "lat": "48.6033", "long": "15.1689"}, {"title": "Lauterach", "lat": "47.4772", "long": "9.7314"}, {"title": "Strasshof an der Nordbahn", "lat": "48.3194", "long": "16.6475"}, {"title": "Bischofshofen", "lat": "47.4172", "long": "13.2194"}, {"title": "Imst", "lat": "47.2394", "long": "10.7381"}, {"title": "Maria Enzersdorf", "lat": "48.1000", "long": "16.2833"}, {"title": "Koflach", "lat": "47.0639", "long": "15.0889"}, {"title": "Rum", "lat": "47.2872", "long": "11.4581"}, {"title": "Laakirchen", "lat": "47.9828", "long": "13.8242"}, {"title": "Judenburg", "lat": "47.1725", "long": "14.6603"}, {"title": "Sankt Andra", "lat": "46.7667", "long": "14.8167"}, {"title": "Purkersdorf", "lat": "48.2092", "long": "16.1792"}, {"title": "Zell am See", "lat": "47.3233", "long": "12.7981"}, {"title": "Altmunster", "lat": "47.9000", "long": "13.7667"}, {"title": "Guntramsdorf", "lat": "48.0483", "long": "16.3150"}, {"title": "Voitsberg", "lat": "47.0483", "long": "15.1503"}, {"title": "Attnang-Puchheim", "lat": "48.0167", "long": "13.7167"}, {"title": "Sierning", "lat": "48.0447", "long": "14.3100"}, {"title": "Sankt Johann in Tirol", "lat": "47.5225", "long": "12.4256"}, {"title": "Sankt Valentin", "lat": "48.1747", "long": "14.5333"}, {"title": "Berndorf", "lat": "47.9428", "long": "16.1036"}, {"title": "Velden am Worthersee", "lat": "46.6125", "long": "14.0419"}, {"title": "Engerwitzdorf", "lat": "48.3397", "long": "14.4256"}, {"title": "Deutsch-Wagram", "lat": "48.2994", "long": "16.5644"}, {"title": "Murzzuschlag", "lat": "47.6075", "long": "15.6731"}, {"title": "Stainz", "lat": "46.8942", "long": "15.2639"}, {"title": "Furstenfeld", "lat": "47.0500", "long": "16.0833"}]