[{"title": "Maputo", "lat": "-25.9667", "long": "32.5833"}, {"title": "Matola", "lat": "-25.9667", "long": "32.4667"}, {"title": "Nampula", "lat": "-15.1167", "long": "39.2667"}, {"title": "Beira", "lat": "-19.8333", "long": "34.8500"}, {"title": "Antonio Enes", "lat": "-16.2333", "long": "39.9167"}, {"title": "Chimoio", "lat": "-19.1167", "long": "33.4500"}, {"title": "Cidade de Nacala", "lat": "-14.5428", "long": "40.6728"}, {"title": "Malema", "lat": "-14.9486", "long": "37.4144"}, {"title": "Quelimane", "lat": "-17.8764", "long": "36.8872"}, {"title": "Tete", "lat": "-16.1667", "long": "33.6000"}, {"title": "Pemba", "lat": "-12.9667", "long": "40.5500"}, {"title": "Lichinga", "lat": "-13.3167", "long": "35.2333"}, {"title": "Xai-Xai", "lat": "-25.0500", "long": "33.6500"}, {"title": "Maxixe", "lat": "-23.8667", "long": "35.3500"}, {"title": "Inhambane", "lat": "-23.8650", "long": "35.3833"}, {"title": "Cuamba", "lat": "-14.8167", "long": "36.5500"}, {"title": "Dondo", "lat": "-19.6167", "long": "34.7500"}, {"title": "Montepuez", "lat": "-13.1167", "long": "39.0000"}, {"title": "Mocuba", "lat": "-16.8500", "long": "36.9833"}, {"title": "Mocuba", "lat": "-16.8496", "long": "38.2600"}, {"title": "Chokwe", "lat": "-24.5253", "long": "33.0086"}, {"title": "Manhica", "lat": "-25.4000", "long": "32.8000"}, {"title": "Chibuto", "lat": "-24.6833", "long": "33.5333"}, {"title": "Pebane", "lat": "-17.2667", "long": "38.1667"}, {"title": "Moatize", "lat": "-16.1167", "long": "33.7333"}, {"title": "Songo", "lat": "-15.6142", "long": "32.7709"}, {"title": "Macomia", "lat": "-12.2377", "long": "40.1190"}, {"title": "Zumbo", "lat": "-15.6167", "long": "30.4500"}, {"title": "Mocimboa da Praia", "lat": "-11.3500", "long": "40.3333"}, {"title": "Namaacha", "lat": "-25.9667", "long": "32.0333"}, {"title": "Catandica", "lat": "-18.0564", "long": "33.1747"}, {"title": "Mocimboa", "lat": "-11.3196", "long": "40.3500"}, {"title": "Manjacaze", "lat": "-24.7117", "long": "33.8828"}, {"title": "Palma", "lat": "-10.7758", "long": "40.4667"}, {"title": "Ulongue", "lat": "-14.7167", "long": "34.3667"}, {"title": "Catembe", "lat": "-26.0050", "long": "32.5597"}, {"title": "Macia", "lat": "-25.0333", "long": "33.1000"}, {"title": "Vilankulo", "lat": "-22.0000", "long": "35.3167"}, {"title": "Mapai", "lat": "-22.7306", "long": "32.0583"}, {"title": "Chinde", "lat": "-18.5833", "long": "36.4667"}, {"title": "Ilha de Mocambique", "lat": "-15.0367", "long": "40.7328"}, {"title": "Inhassoro", "lat": "-21.5333", "long": "35.2000"}, {"title": "Manica", "lat": "-18.9344", "long": "32.8756"}, {"title": "Espungabera", "lat": "-20.4531", "long": "32.7725"}, {"title": "Zavora", "lat": "-24.5167", "long": "35.2000"}, {"title": "Marrupa", "lat": "-13.1833", "long": "37.5000"}, {"title": "Nicoadala", "lat": "-17.6077", "long": "36.8197"}, {"title": "Ligonha", "lat": "-15.1757", "long": "37.7400"}, {"title": "Regedor Quissico", "lat": "-24.7257", "long": "34.7660"}, {"title": "Massangena", "lat": "-21.5378", "long": "32.9564"}, {"title": "Panda", "lat": "-24.0629", "long": "34.7303"}, {"title": "Chiramba", "lat": "-16.8921", "long": "34.6559"}]